sourcepredict/__init__.py
sourcepredict/__main__.py
sourcepredict/sourcepredictlib/__init__.py
sourcepredict/sourcepredictlib/ml.py
sourcepredict/sourcepredictlib/normalize.py
sourcepredict/sourcepredictlib/utils.py
sourcepredict-0.5.1.dist-info/LICENSE
sourcepredict-0.5.1.dist-info/METADATA
sourcepredict-0.5.1.dist-info/WHEEL
sourcepredict-0.5.1.dist-info/entry_points.txt
sourcepredict-0.5.1.dist-info/top_level.txt
sourcepredict-0.5.1.dist-info/RECORD
