Metadata-Version: 2.1
Name: sourcepredict
Version: 0.5.1
Summary: Classification and prediction of the origin of metagenomic samples
Home-page: https://github.com/maxibor/sourcepredict
License: GPLv3
Platform: UNKNOWN
Requires-Python: >=3.6
License-File: LICENSE
Requires-Dist: numpy>=1.16.4
Requires-Dist: pandas>=0.24.1
Requires-Dist: scikit-learn>=0.20.1
Requires-Dist: scikit-bio>=0.5.5
Requires-Dist: umap-learn>=0.3.7
Requires-Dist: scipy>=1.1.0
Requires-Dist: ete3>=3.1.1
